[
    {
        "title": "My life at Liz Claiborne : how we broke the rules and built the largest fashion company in the world : a business memoir",
        "author": "Chazen, Jerome A.",
        "onesearch-url": "https://onesearch.fitnyc.edu/discovery/fulldisplay?docid=alma990001351540204829&context=L&vid=01SUNY_FIT:01SUNY_FIT&search_scope=MyInst_and_CI&tab=Everything&lang=en",
        "call-number": "HD9940.U6 L58 2011",
        "cover-url": "https://books.google.com/books/content?id=r_8xuAAACAAJ&printsec=frontcover&img=1&zoom=1&source=gbs_api",
        "created": "2026-06-22"
    },
    {
        "title": "Equestrian : the ultimate book",
        "author": "Brandt, Alena, author.",
        "onesearch-url": "https://onesearch.fitnyc.edu/discovery/fulldisplay?docid=alma992056964204829&context=L&vid=01SUNY_FIT:01SUNY_FIT&search_scope=MyInst_and_CI&tab=Everything&lang=en",
        "call-number": "SF294.2 .B73 2025",
        "cover-url": "https://books.google.com/books/content?id=I4t90QEACAAJ&printsec=frontcover&img=1&zoom=1&source=gbs_api",
        "created": "2026-06-18"
    },
    {
        "title": "Marcus Jansen : decade",
        "author": "Jansen, Marcus, 1968- artist.",
        "onesearch-url": "https://onesearch.fitnyc.edu/discovery/fulldisplay?docid=alma992056966304829&context=L&vid=01SUNY_FIT:01SUNY_FIT&search_scope=MyInst_and_CI&tab=Everything&lang=en",
        "call-number": "ND237.J325 A4 2015",
        "cover-url": "https://books.google.com/books/content?id=G21jjwEACAAJ&printsec=frontcover&img=1&zoom=1&source=gbs_api",
        "created": "2026-06-18"
    },
    {
        "title": "Making and breaking the grid : a graphic design layout workshop",
        "author": "Samara, Timothy, author.",
        "onesearch-url": "https://onesearch.fitnyc.edu/discovery/fulldisplay?docid=alma992055669504829&context=L&vid=01SUNY_FIT:01SUNY_FIT&search_scope=MyInst_and_CI&tab=Everything&lang=en",
        "call-number": "Z246 .S23 2023",
        "cover-url": "https://books.google.com/books/content?id=Xf-pEAAAQBAJ&printsec=frontcover&img=1&zoom=1&edge=curl&source=gbs_api",
        "created": "2026-06-11"
    },
    {
        "title": "Copenhagen : in fashion",
        "author": "Toromanoff, Pierre",
        "onesearch-url": "https://onesearch.fitnyc.edu/discovery/fulldisplay?docid=alma992056869404829&context=L&vid=01SUNY_FIT:01SUNY_FIT&search_scope=MyInst_and_CI&tab=Everything&lang=en",
        "call-number": "TT504.6.D4 T67 2026",
        "cover-url": "https://books.google.com/books/content?id=MdOi0QEACAAJ&printsec=frontcover&img=1&zoom=1&source=gbs_api",
        "created": "2026-06-10"
    },
    {
        "title": "Rick Owens : temple of love",
        "author": "Owens, Rick, 1961- author.",
        "onesearch-url": "https://onesearch.fitnyc.edu/discovery/fulldisplay?docid=alma992055469204829&context=L&vid=01SUNY_FIT:01SUNY_FIT&search_scope=MyInst_and_CI&tab=Everything&lang=en",
        "call-number": "TT505.O94 R53 2025",
        "cover-url": "https://books.google.com/books/content?id=Q_shEQAAQBAJ&printsec=frontcover&img=1&zoom=1&edge=curl&source=gbs_api",
        "created": "2026-06-10"
    }
]